{"table":[{"key":"Turbine Details","value":" VSTWWIWMWL'B"},{"key":"Nacelle ID","value":" P9090009/5I383"},{"key":"2. NAME OF THE TURBINE & NO. :","value":"MSII.\"JASMIN..MEI.....8F’..—.02..................."},{"key":"Turbine Make","value":" . VEST/AS"},{"key":"4. NAME OF THE CUSTOMER :","value":".BFIIIISR..\"RAMAKIUM...(.€I:(1.4.N...JALKA.)..."},{"key":"‘- 7. PHONE NO. OF THE CUSTOMER‘S SITE:","value":"...OFLSIJELQHQQ—FL.........................................."},{"key":"Date of Commissioning","value":" QAJORWA"},{"key":"C. YAW MOTOR MAKE & SI. NO. :","value":"ISQGIEHBX’P\"H9.G..’.‘.‘.°!.2...'.‘.F‘/...3'.°.FI5..6.€‘1.45.?53WJX/ 70W”?"},{"key":"HYD","value":", BRAKE SYSTEM MAKE & SI. NO. BMWUIVM‘ZPW"},{"key":"Anemometer","value":" N‘L"},{"key":"Wind Vane","value":" N'L"},{"key":"Pull Chord","value":" '"},{"key":"Vibration Switch","value":" SUU‘IK/PQ"},{"key":"Year of Manufacturing","value":" 90%"}]}